LICENSE
MANIFEST.in
README.rst
setup.cfg
setup.py
django_celery_extensions/__init__.py
django_celery_extensions/apps.py
django_celery_extensions/beat.py
django_celery_extensions/celery.py
django_celery_extensions/checks.py
django_celery_extensions/config.py
django_celery_extensions/task.py
django_celery_extensions.egg-info/PKG-INFO
django_celery_extensions.egg-info/SOURCES.txt
django_celery_extensions.egg-info/dependency_links.txt
django_celery_extensions.egg-info/entry_points.txt
django_celery_extensions.egg-info/not-zip-safe
django_celery_extensions.egg-info/requires.txt
django_celery_extensions.egg-info/top_level.txt
django_celery_extensions/bin/__init__.py
django_celery_extensions/bin/celeryautoreload.py
example/__init__.py
example/manage.py
example/urls.py
example/wsgi.py
example/app/__init__.py
example/app/models.py
example/app/tasks.py
example/app/tests.py
example/app/management/__init__.py
example/app/management/commands/__init__.py
example/app/management/commands/create_user.py
example/settings/__init__.py
example/settings/celery.py
example/settings/settings.py