Metadata-Version: 2.1
Name: django-celery-extensions
Version: 0.0.38
Summary: Django celery extensions library.
Home-page: https://github.com/druids/django-celery-extensions
Author: Lubos Matl
Author-email: matllubos@gmail.com
License: MIT
Keywords: django,celery
Platform: UNKNOWN
Classifier: Development Status :: 3 - Alpha
Classifier: Environment :: Web Environment
Classifier: Framework :: Django
Classifier: Intended Audience :: Developers
Classifier: Intended Audience :: End Users/Desktop
Classifier: License :: OSI Approved :: MIT License
Classifier: Natural Language :: Czech
Classifier: Operating System :: OS Independent
Classifier: Programming Language :: Python
Classifier: Topic :: Internet :: WWW/HTTP :: Dynamic Content
Classifier: Topic :: Internet :: WWW/HTTP :: Site Management
